django_ricker/__init__.py
django_ricker/urls.py
django_ricker-0.0.3.dist-info/LICENSE
django_ricker-0.0.3.dist-info/METADATA
django_ricker-0.0.3.dist-info/WHEEL
django_ricker-0.0.3.dist-info/top_level.txt
django_ricker-0.0.3.dist-info/RECORD
