Metadata-Version: 2.1
Name: django-ricker
Version: 0.0.3
Summary: django some utils, make it convenient for work. 
Home-page: https://github.com/weihuchao/django_utils
Author: weihuchao
Author-email: weihuchao@gmail.com
License: UNKNOWN
Platform: UNKNOWN
Classifier: Intended Audience :: Developers
Classifier: License :: OSI Approved :: MIT License
Classifier: Operating System :: OS Independent
